pynfra/__init__.py
pynfra/main.py
pynfra/pynfra.py
pynfra/test_recipe.py
pynfra/modules/__init__.py
pynfra/modules/classes.py
pynfra/modules/config.py
pynfra/modules/db.py
pynfra/modules/node.py
pynfra/modules/ssh_keys.py
pynfra/modules/tui.py
pynfra/recipes/__init__.py
pynfra/recipes/debian_11_torbridge_install.py
pynfra-0.1.3.dist-info/LICENSE
pynfra-0.1.3.dist-info/METADATA
pynfra-0.1.3.dist-info/WHEEL
pynfra-0.1.3.dist-info/entry_points.txt
pynfra-0.1.3.dist-info/top_level.txt
pynfra-0.1.3.dist-info/RECORD
