Metadata-Version: 2.1
Name: pynfra
Version: 0.1.3
Summary: A console utility to bring up new Tor bridges easily
Home-page: https://github.com/gergelykalman/pynfra
Author: Gergely Kalman
Author-email: g@gergelykalman.com
License: UNKNOWN
Project-URL: Bug Reports, https://github.com/gergelykalman/pynfra/issues
Project-URL: Say Thanks!, https://twitter.com/gergely_kalman
Project-URL: Source, https://github.com/gergelykalman/pynfra
Keywords: python,cloud,configuration-management,remote-execution,infrastructure,devops,provisioning
Platform: UNKNOWN
Classifier: Development Status :: 4 - Beta
Classifier: Environment :: Console
Classifier: Intended Audience :: Developers
Classifier: Intended Audience :: System Administrators
Classifier: Topic :: System :: Installation/Setup
Classifier: Topic :: System :: Systems Administration
Classifier: Topic :: Utilities
Classifier: License :: OSI Approved :: MIT License
Classifier: Programming Language :: Python :: 3
Classifier: Programming Language :: Python :: 3.6
Classifier: Programming Language :: Python :: 3.7
Classifier: Programming Language :: Python :: 3.8
Classifier: Programming Language :: Python :: 3.9
Classifier: Programming Language :: Python :: 3.10
Classifier: Programming Language :: Python :: 3 :: Only
Requires-Python: >=3.6, <4
License-File: LICENSE
Requires-Dist: paramiko
